gaiaxpy/__init__.py
gaiaxpy/calibrator/__init__.py
gaiaxpy/calibrator/calibrator.py
gaiaxpy/calibrator/external_instrument_model.py
gaiaxpy/cholesky/__init__.py
gaiaxpy/cholesky/cholesky.py
gaiaxpy/colour_equation/__init__.py
gaiaxpy/colour_equation/xp_filter_system_colour_equation.py
gaiaxpy/config/OptimisedCalibratedBases_BpId32_RpId37_withNormalisation.xml
gaiaxpy/config/TabulatedDispersionFunction-DR3-v375wiv142r_20200610.csv
gaiaxpy/config/__init__.py
gaiaxpy/config/available_systems.txt
gaiaxpy/config/bpC03_v211w_bases.csv
gaiaxpy/config/bpC03_v211w_dispersion.csv
gaiaxpy/config/bpC03_v211w_response.csv
gaiaxpy/config/bpC03_v375wi_bases.csv
gaiaxpy/config/bpC03_v375wi_dispersion.csv
gaiaxpy/config/bpC03_v375wi_response.csv
gaiaxpy/config/config.ini
gaiaxpy/config/fluxCal_20230901_renorm_bspline.xml
gaiaxpy/config/paths.py
gaiaxpy/config/rpC03_v142r_bases.csv
gaiaxpy/config/rpC03_v142r_dispersion.csv
gaiaxpy/config/rpC03_v142r_response.csv
gaiaxpy/config/colour_eq_files/JkcStd_colour_eq.ini
gaiaxpy/config/colour_eq_files/SdssStd_colour_eq.ini
gaiaxpy/config/correction_tables/DIDREQ-465-ElsCustomW09S2-correction-factors.csv
gaiaxpy/config/correction_tables/DIDREQ-465-EuclidVis-correction-factors.csv
gaiaxpy/config/correction_tables/DIDREQ-465-Gaia2-correction-factors.csv
gaiaxpy/config/correction_tables/DIDREQ-465-GaiaDr3Vega-correction-factors.csv
gaiaxpy/config/correction_tables/DIDREQ-465-HipparcosTycho-correction-factors-old.csv
gaiaxpy/config/correction_tables/DIDREQ-465-HipparcosTycho-correction-factors.csv
gaiaxpy/config/correction_tables/DIDREQ-465-HstAcswfc-correction-factors.csv
gaiaxpy/config/correction_tables/DIDREQ-465-HstHugsStd-correction-factors.csv
gaiaxpy/config/correction_tables/DIDREQ-465-HstWfc3uvis-correction-factors.csv
gaiaxpy/config/correction_tables/DIDREQ-465-HstWfpc2-correction-factors.csv
gaiaxpy/config/correction_tables/DIDREQ-465-Iphas-correction-factors.csv
gaiaxpy/config/correction_tables/DIDREQ-465-Jkc-correction-factors.csv
gaiaxpy-2.1.4.dist-info/METADATA
gaiaxpy-2.1.4.dist-info/WHEEL
gaiaxpy-2.1.4.dist-info/licenses/LICENSE
gaiaxpy-2.1.4.dist-info/RECORD
