Metadata-Version: 2.4
Name: GaiaXPy
Version: 2.1.4
Summary: Utilities to handle BP/RP (XP) Gaia low-resolution spectra as delivered via the Archive.
Project-URL: homepage, https://gaia-dpci.github.io/GaiaXPy-website/
Project-URL: documentation, https://gaiaxpy.readthedocs.io/en/latest/
Author: Lovro Palaversa
Author-email: Francesca De Angeli <fda@ast.cam.ac.uk>, Paolo Montegriffo <paolo.montegriffo@inaf.it>, Daniela Ruz-Mieres <dr540@ast.cam.ac.uk>
Maintainer-email: Daniela Ruz-Mieres <dr540@ast.cam.ac.uk>
License-Expression: BSD-3-Clause
License-File: LICENSE
Classifier: Operating System :: OS Independent
Classifier: Programming Language :: Python :: 3
Requires-Python: >=3.10
Requires-Dist: aenum
Requires-Dist: astropy!=7.0.0,!=7.0.1,>=5.3.3
Requires-Dist: astroquery
Requires-Dist: fastavro
Requires-Dist: hdfs
Requires-Dist: matplotlib
Requires-Dist: numpy
Requires-Dist: packaging
Requires-Dist: pandas>=1.5.0
Requires-Dist: scipy
Requires-Dist: tqdm>=4.66.3
Provides-Extra: dev
Requires-Dist: flake8; extra == 'dev'
Requires-Dist: pytest; extra == 'dev'
Requires-Dist: pytest-cov; extra == 'dev'
Requires-Dist: pytest-mock; extra == 'dev'
Provides-Extra: docs
Requires-Dist: hatch; extra == 'docs'
Requires-Dist: sphinx; extra == 'docs'
Requires-Dist: sphinx-rtd-theme; extra == 'docs'
